sparrow_order_lib/__init__.py
sparrow_order_lib/example.py
sparrow_order_lib/core/__init__.py
sparrow_order_lib/core/base_models.py
sparrow_order_lib/core/common_utils.py
sparrow_order_lib/core/constants.py
sparrow_order_lib/core/datastructures.py
sparrow_order_lib/core/decorators.py
sparrow_order_lib/core/dt_utils.py
sparrow_order_lib/core/formats.py
sparrow_order_lib/core/model_function.py
sparrow_order_lib/core/numbers.py
sparrow_order_lib/core/text.py
sparrow_order_lib/core/xls_util.py
sparrow_order_lib/db_tool/__init__.py
sparrow_order_lib/db_tool/query.py
sparrow_order_lib/es/__init__.py
sparrow_order_lib/es/constants.py
sparrow_order_lib/es/mapping_constants.py
sparrow_order_lib/es/query_mapping_constants.py
sparrow_order_lib/es/test_order_doc_type.py
sparrow_order_lib/es/es_util/__init__.py
sparrow_order_lib/es/es_util/base.py
sparrow_order_lib/es/es_util/client.py
sparrow_order_lib/es/es_util/constants.py
sparrow_order_lib/es/es_util/es_builder.py
sparrow_order_lib/es/es_util/es_door.py
sparrow_order_lib/es/es_util/es_param.py
sparrow_order_lib/es/es_util/es_query_util.py
sparrow_order_lib/es/es_util/exceptions.py
sparrow_order_lib/es/es_util/field.py
sparrow_order_lib/es/es_util/in_query_param.py
sparrow_order_lib/es/es_util/index.py
sparrow_order_lib/es/es_util/mock.py
sparrow_order_lib/es/es_util/operators.py
sparrow_order_lib/es/es_util/tests/__init__.py
sparrow_order_lib/es/es_util/tests/test_base.py
sparrow_order_lib/es/es_util/tests/test_client.py
sparrow_order_lib/es/es_util/tests/test_es_builder.py
sparrow_order_lib/es/es_util/tests/test_es_door.py
sparrow_order_lib/es/es_util/tests/test_es_param.py
sparrow_order_lib/es/es_util/tests/test_es_query_util.py
sparrow_order_lib/es/es_util/tests/test_field.py
sparrow_order_lib/es/es_util/tests/test_in_query_param.py
sparrow_order_lib/es/es_util/tests/test_mock.py
sparrow_order_lib/es/es_util/tests/test_operators.py
sparrow_order_lib/remote_call/__init__.py
sparrow_order_lib-1.0.8.dist-info/LICENSE
sparrow_order_lib-1.0.8.dist-info/METADATA
sparrow_order_lib-1.0.8.dist-info/WHEEL
sparrow_order_lib-1.0.8.dist-info/top_level.txt
sparrow_order_lib-1.0.8.dist-info/RECORD
