Metadata-Version: 2.1
Name: sparrow-order-lib
Version: 1.0.8
Summary: This is a lib for sparrow order projects.
Home-page: https://gitee.com/sparrow614/sparrow-order-lib
Author: Jessica Liao
Author-email: 18610193367@sina.cn
Project-URL: Bug Tracker, https://gitee.com/sparrow614/sparrow-order-lib/issues
Classifier: Programming Language :: Python :: 3
Classifier: License :: OSI Approved :: MIT License
Classifier: Operating System :: OS Independent
Requires-Python: >=3.7
License-File: LICENSE
Requires-Dist: XlsxWriter ~=3.0.3
Requires-Dist: elasticsearch ==7.8.0
